smartmultiprocessing/__init__.py
smartmultiprocessing/_sphandler.py
smartmultiprocessing/errors.py
smartmultiprocessing/pool.py
smartmultiprocessing/process.py
smartmultiprocessing/queue.py
smartmultiprocessing/utilities.py
smartmultiprocessing-0.0.1.dist-info/LICENSE
smartmultiprocessing-0.0.1.dist-info/METADATA
smartmultiprocessing-0.0.1.dist-info/WHEEL
smartmultiprocessing-0.0.1.dist-info/top_level.txt
smartmultiprocessing-0.0.1.dist-info/RECORD
